polycons/__init__.py
polycons/py.typed
polycons/_jsii/__init__.py
polycons/_jsii/polycons@0.1.9.jsii.tgz
polycons-0.1.9.dist-info/LICENSE
polycons-0.1.9.dist-info/METADATA
polycons-0.1.9.dist-info/WHEEL
polycons-0.1.9.dist-info/top_level.txt
polycons-0.1.9.dist-info/RECORD
