Metadata-Version: 2.1
Name: polycons
Version: 0.1.9
Summary: polycons
Home-page: https://github.com/winglang/polycons
Author: Monada, Inc.<ping@monada.co>
License: MIT
Project-URL: Source, https://github.com/winglang/polycons
Platform: UNKNOWN
Classifier: Intended Audience :: Developers
Classifier: Operating System :: OS Independent
Classifier: Programming Language :: JavaScript
Classifier: Programming Language :: Python :: 3 :: Only
Classifier: Programming Language :: Python :: 3.7
Classifier: Programming Language :: Python :: 3.8
Classifier: Programming Language :: Python :: 3.9
Classifier: Programming Language :: Python :: 3.10
Classifier: Typing :: Typed
Classifier: Development Status :: 5 - Production/Stable
Classifier: License :: OSI Approved
Requires-Python: ~=3.7
License-File: LICENSE
Requires-Dist: constructs (<11.0.0,>=10.0.25)
Requires-Dist: jsii (<2.0.0,>=1.73.0)
Requires-Dist: publication (>=0.0.3)
Requires-Dist: typeguard (~=2.13.3)
